{"id": 120001083376, "nomeUrna": "DANTHY", "numero": 40888, "idCandidatoSuperior": 0, "nomeCompleto": "DANTHYELLE MELGAR DE JESUS", "descricaoSexo": "FEM.", "dataDeNascimento": "1993-05-27", "tituloEleitor": "023798241961", "cpf": "04847078179", "descricaoEstadoCivil": "Solteiro(a)", "descricaoCorRaca": "PARDA", "descricaoSituacao": "Aguardando julgamento", "nacionalidade": "Brasileira nata", "grauInstrucao": "Ensino M\u00e9dio completo", "ocupacao": "Motorista Particular", "gastoCampanha1T": 19760.93, "gastoCampanha2T": 0, "sgUfNascimento": "MS", "nomeMunicipioNascimento": "CORUMB\u00c1", "localCandidatura": "LAD\u00c1RIO", "ufCandidatura": "91030", "ufSuperiorCandidatura": "MS", "dataUltimaAtualizacao": "2020-10-07", "fotoUrl": "http://divulgacandcontas.tse.jus.br/candidaturas/oficial/2020/MS/91030/426/candidatos/514920/foto.jpg", "fotoDataUltimaAtualizacao": null, "descricaoTotalizacao": "Concorrendo", "nomeColigacao": "PSB", "composicaoColigacao": "**", "numeroProcessoDrap": "06001564320206120050", "numeroProcessoDrapEncrypt": "6471a10b42417ba29beb4e5b4f649f49f5d558df65d1b2b83c94518a892104aaa51fc66567b5510d", "numeroProcesso": "06001746420206120050", "numeroProcessoEncrypt": "1bd2fb89584a4e995f826e62a70b508ff5d558df65d1b2b83c94518a892104aaa51fc66567b5510d", "numeroProcessoPrestContas": null, "numeroProcessoPrestContasEncrypt": null, "numeroProtocolo": null, "cargo": {"codigo": 13, "sigla": null, "nome": "Vereador", "codSuperior": 0, "titular": true, "contagem": 0}, "bens": [], "totalDeBens": 0, "vices": null, "partido": {"numero": 40, "sigla": "PSB", "nome": "Partido Socialista Brasileiro"}, "eleicao": {"id": 2030402020, "siglaUF": null, "localidadeSgUe": null, "ano": 2020, "codigo": null, "nomeEleicao": null, "tipoEleicao": null, "turno": null, "tipoAbrangencia": null, "dataEleicao": null, "codSituacaoEleicao": null, "descricaoSituacaoEleicao": null, "descricaoEleicao": "2020"}, "emails": ["e.petzold10@gmail.com"], "sites": [], "arquivos": [{"idArquivo": 120008893837, "nome": "11_1600784305771.pdf", "url": "candidaturas/oficial/2020/MS/91030/426/candidatos/514920/", "tipo": "pdf", "codTipo": "11", "fullFilePath": null, "fileInputStream": null, "fileByteArray": null}, {"idArquivo": 120008893834, "nome": "12_1600784325713.pdf", "url": "candidaturas/oficial/2020/MS/91030/426/candidatos/514920/", "tipo": "pdf", "codTipo": "12", "fullFilePath": null, "fileInputStream": null, "fileByteArray": null}, {"idArquivo": 120008893833, "nome": "14_1600784285049.pdf", "url": "candidaturas/oficial/2020/MS/91030/426/candidatos/514920/", "tipo": "pdf", "codTipo": "14", "fullFilePath": null, "fileInputStream": null, "fileByteArray": null}, {"idArquivo": 120008893832, "nome": "13_1600784347745.pdf", "url": "candidaturas/oficial/2020/MS/91030/426/candidatos/514920/", "tipo": "pdf", "codTipo": "13", "fullFilePath": null, "fileInputStream": null, "fileByteArray": null}], "eleicoesAnteriores": [{"nrAno": 2020, "id": "120001083376", "nomeUrna": "DANTHY", "nomeCandidato": "DANTHYELLE MELGAR DE JESUS", "idEleicao": "2030402020", "sgUe": "91030", "local": "LAD\u00c1RIO", "cargo": "Vereador", "partido": "PSB", "situacaoTotalizacao": "Concorrendo", "txLink": "http://divulgacandcontas.tse.jus.br/divulga/#/candidato/2020/2030402020/91030/120001083376"}, {"nrAno": 2016, "id": "120000001975", "nomeUrna": "DANTHYELLE MELGAR", "nomeCandidato": "DANTHYELLE MELGAR DE JESUS", "idEleicao": "2", "sgUe": "91030", "local": "LAD\u00c1RIO", "cargo": "Vereador", "partido": "PPS", "situacaoTotalizacao": "Suplente", "txLink": "http://divulgacandcontas.tse.jus.br/divulga/#/candidato/2016/2/91030/120000001975"}], "substituto": null, "motivos": null, "codigoSituacaoCandidato": 8, "descricaoSituacaoCandidato": "CADASTRADO", "st_MOTIVO_GASTO_ILICITO": false, "st_DIVULGA_ARQUIVOS": false, "st_SUBSTITUIDO": false, "st_MOTIVO_FICHA_LIMPA": false, "st_MOTIVO_COMPRA_VOTO": false, "st_MOTIVO_CONDUTA_VEDADA": false, "ds_MOTIVO_OUTROS": null, "st_MOTIVO_AUSENCIA_REQUISITO": false, "st_MOTIVO_IND_PARTIDO": false, "cnpjcampanha": "38965046000118", "gastoCampanha": 0.0, "st_DIVULGA": true, "st_REELEICAO": false, "st_MOTIVO_ABUSO_PODER": false, "st_DIVULGA_BENS": true, "descricaoNaturalidade": "MS-CORUMB\u00c1"}