{"id": 120000858292, "nomeUrna": "NAIR OLIVEIRA", "numero": 45678, "idCandidatoSuperior": 0, "nomeCompleto": "NAIR OLIVEIRA SILVA", "descricaoSexo": "FEM.", "dataDeNascimento": "1964-01-02", "tituloEleitor": "002003661902", "cpf": "31316166104", "descricaoEstadoCivil": "Divorciado(a)", "descricaoCorRaca": "BRANCA", "descricaoSituacao": "Aguardando julgamento", "nacionalidade": "Brasileira nata", "grauInstrucao": "Ensino M\u00e9dio completo", "ocupacao": "Servidor P\u00fablico Civil Aposentado", "gastoCampanha1T": 24494.06, "gastoCampanha2T": 0, "sgUfNascimento": "MS", "nomeMunicipioNascimento": "RIO NEGRO", "localCandidatura": "RIO NEGRO", "ufCandidatura": "91456", "ufSuperiorCandidatura": "MS", "dataUltimaAtualizacao": "2020-09-26", "fotoUrl": "http://divulgacandcontas.tse.jus.br/candidaturas/oficial/2020/MS/91456/426/candidatos/481954/foto.jpg", "fotoDataUltimaAtualizacao": null, "descricaoTotalizacao": "Concorrendo", "nomeColigacao": "PSDB", "composicaoColigacao": "**", "numeroProcessoDrap": "06001523620206120040", "numeroProcessoDrapEncrypt": "2d6511624d18336b73b4f48e50810d1e5a9ffdf0456f62623c94518a892104aaa51fc66567b5510d", "numeroProcesso": "06001662020206120040", "numeroProcessoEncrypt": "3cad738c388988c734fb35f205ba00bf5a9ffdf0456f62623c94518a892104aaa51fc66567b5510d", "numeroProcessoPrestContas": null, "numeroProcessoPrestContasEncrypt": null, "numeroProtocolo": null, "cargo": {"codigo": 13, "sigla": null, "nome": "Vereador", "codSuperior": 0, "titular": true, "contagem": 0}, "bens": [{"ordem": 1, "descricao": "IMOVEL RESIDENCIAL - RIO NEGRO MS", "descricaoDeTipoDeBem": "Casa", "valor": 30000.0, "dataUltimaAtualizacao": "2020-09-23"}, {"ordem": 2, "descricao": "VEICULO RENAULT/SANDEIRO EXP 16V PRATA 2013", "descricaoDeTipoDeBem": "Ve\u00edculo automotor terrestre: caminh\u00e3o, autom\u00f3vel, moto, etc.", "valor": 42050.0, "dataUltimaAtualizacao": "2020-09-23"}], "totalDeBens": 72050, "vices": null, "partido": {"numero": 45, "sigla": "PSDB", "nome": "Partido da Social Democracia Brasileira"}, "eleicao": {"id": 2030402020, "siglaUF": null, "localidadeSgUe": null, "ano": 2020, "codigo": null, "nomeEleicao": null, "tipoEleicao": null, "turno": null, "tipoAbrangencia": null, "dataEleicao": null, "codSituacaoEleicao": null, "descricaoSituacaoEleicao": null, "descricaoEleicao": "2020"}, "emails": ["edsonrionegro@hotmail.com", "naninha-50-@hotmail.com"], "sites": [], "arquivos": [{"idArquivo": 120007356760, "nome": "14_1600804828643.pdf", "url": "candidaturas/oficial/2020/MS/91456/426/candidatos/481954/", "tipo": "pdf", "codTipo": "14", "fullFilePath": null, "fileInputStream": null, "fileByteArray": null}, {"idArquivo": 120007356759, "nome": "13_1600804827929.pdf", "url": "candidaturas/oficial/2020/MS/91456/426/candidatos/481954/", "tipo": "pdf", "codTipo": "13", "fullFilePath": null, "fileInputStream": null, "fileByteArray": null}, {"idArquivo": 120007356758, "nome": "12_1600804827310.pdf", "url": "candidaturas/oficial/2020/MS/91456/426/candidatos/481954/", "tipo": "pdf", "codTipo": "12", "fullFilePath": null, "fileInputStream": null, "fileByteArray": null}, {"idArquivo": 120007356757, "nome": "11_1600804826568.pdf", "url": "candidaturas/oficial/2020/MS/91456/426/candidatos/481954/", "tipo": "pdf", "codTipo": "11", "fullFilePath": null, "fileInputStream": null, "fileByteArray": null}], "eleicoesAnteriores": [{"nrAno": 2020, "id": "120000858292", "nomeUrna": "NAIR OLIVEIRA", "nomeCandidato": "NAIR OLIVEIRA SILVA", "idEleicao": "2030402020", "sgUe": "91456", "local": "RIO NEGRO", "cargo": "Vereador", "partido": "PSDB", "situacaoTotalizacao": "Concorrendo", "txLink": "http://divulgacandcontas.tse.jus.br/divulga/#/candidato/2020/2030402020/91456/120000858292"}], "substituto": null, "motivos": null, "codigoSituacaoCandidato": 8, "descricaoSituacaoCandidato": "CADASTRADO", "st_SUBSTITUIDO": false, "descricaoNaturalidade": "MS-RIO NEGRO", "st_MOTIVO_AUSENCIA_REQUISITO": false, "st_MOTIVO_CONDUTA_VEDADA": false, "cnpjcampanha": "38788047000134", "gastoCampanha": 0.0, "st_MOTIVO_ABUSO_PODER": false, "st_MOTIVO_COMPRA_VOTO": false, "ds_MOTIVO_OUTROS": null, "st_MOTIVO_GASTO_ILICITO": false, "st_MOTIVO_IND_PARTIDO": false, "st_MOTIVO_FICHA_LIMPA": false, "st_DIVULGA_ARQUIVOS": false, "st_DIVULGA_BENS": true, "st_DIVULGA": true, "st_REELEICAO": false}