{"id": 120001123699, "nomeUrna": "GILMAR CRUZ", "numero": 12999, "idCandidatoSuperior": 0, "nomeCompleto": "GILMAR DA CRUZ SILVA", "descricaoSexo": "MASC.", "dataDeNascimento": "1963-11-02", "tituloEleitor": "000992641902", "cpf": "30871484153", "descricaoEstadoCivil": "Divorciado(a)", "descricaoCorRaca": "PRETA", "descricaoSituacao": "Aguardando julgamento", "nacionalidade": "Brasileira nata", "grauInstrucao": "Ensino M\u00e9dio completo", "ocupacao": "Aposentado (Exceto Servidor P\u00fablico)", "gastoCampanha1T": 94207.39, "gastoCampanha2T": 0, "sgUfNascimento": "MS", "nomeMunicipioNascimento": "PARANA\u00cdBA", "localCandidatura": "PARANA\u00cdBA", "ufCandidatura": "91251", "ufSuperiorCandidatura": "MS", "dataUltimaAtualizacao": "2020-10-08", "fotoUrl": "http://divulgacandcontas.tse.jus.br/candidaturas/oficial/2020/MS/91251/426/candidatos/752134/foto.JPG", "fotoDataUltimaAtualizacao": null, "descricaoTotalizacao": "Concorrendo", "nomeColigacao": "PDT", "composicaoColigacao": "**", "numeroProcessoDrap": "06001331420206120013", "numeroProcessoDrapEncrypt": "b382a4dcf053e5135f826e62a70b508f0fea86130b6b98c63c94518a892104aaa51fc66567b5510d", "numeroProcesso": "06001712620206120013", "numeroProcessoEncrypt": "22fde7c0565dac8a73b4f48e50810d1e0fea86130b6b98c63c94518a892104aaa51fc66567b5510d", "numeroProcessoPrestContas": null, "numeroProcessoPrestContasEncrypt": null, "numeroProtocolo": null, "cargo": {"codigo": 13, "sigla": null, "nome": "Vereador", "codSuperior": 0, "titular": true, "contagem": 0}, "bens": [{"ordem": 2, "descricao": "TERRENO EM CAMPO GRANDE", "descricaoDeTipoDeBem": "Terreno", "valor": 3358.55, "dataUltimaAtualizacao": "2020-09-25"}, {"ordem": 1, "descricao": "TERRENO EM PARANAIBA", "descricaoDeTipoDeBem": "Terreno", "valor": 66792.7, "dataUltimaAtualizacao": "2020-09-25"}], "totalDeBens": 70151.25, "vices": null, "partido": {"numero": 12, "sigla": "PDT", "nome": "Partido Democr\u00e1tico Trabalhista"}, "eleicao": {"id": 2030402020, "siglaUF": null, "localidadeSgUe": null, "ano": 2020, "codigo": null, "nomeEleicao": null, "tipoEleicao": null, "turno": null, "tipoAbrangencia": null, "dataEleicao": null, "codSituacaoEleicao": null, "descricaoSituacaoEleicao": null, "descricaoEleicao": "2020"}, "emails": ["equisamoveis@hotmail.com"], "sites": [], "arquivos": [{"idArquivo": 120010303473, "nome": "pje-a90f45a6-Certid\u00e3o criminal da Justi\u00e7a Federal de 1\u00ba grau.pdf", "url": "candidaturas/oficial/2020/MS/91251/426/candidatos/120001123699/", "tipo": "pdf", "codTipo": "11", "fullFilePath": null, "fileInputStream": null, "fileByteArray": null}, {"idArquivo": 120010303472, "nome": "pje-0becab9d-Certid\u00e3o criminal da Justi\u00e7a Estadual de 1\u00ba grau.pdf", "url": "candidaturas/oficial/2020/MS/91251/426/candidatos/120001123699/", "tipo": "pdf", "codTipo": "13", "fullFilePath": null, "fileInputStream": null, "fileByteArray": null}, {"idArquivo": 120010303471, "nome": "pje-aef7b975-Certid\u00e3o criminal da Justi\u00e7a Estadual de 2\u00ba grau.pdf", "url": "candidaturas/oficial/2020/MS/91251/426/candidatos/120001123699/", "tipo": "pdf", "codTipo": "14", "fullFilePath": null, "fileInputStream": null, "fileByteArray": null}, {"idArquivo": 120010303426, "nome": "pje-7005e5fd-Certid\u00e3o criminal da Justi\u00e7a Estadual de 2\u00ba grau.pdf", "url": "candidaturas/oficial/2020/MS/91251/426/candidatos/120001123699/", "tipo": "pdf", "codTipo": "14", "fullFilePath": null, "fileInputStream": null, "fileByteArray": null}, {"idArquivo": 120009169778, "nome": "CF2.pdf", "url": "candidaturas/oficial/2020/MS/91251/426/candidatos/752134/", "tipo": "pdf", "codTipo": "12", "fullFilePath": null, "fileInputStream": null, "fileByteArray": null}], "eleicoesAnteriores": [{"nrAno": 2020, "id": "120001123699", "nomeUrna": "GILMAR CRUZ", "nomeCandidato": "GILMAR DA CRUZ SILVA", "idEleicao": "2030402020", "sgUe": "91251", "local": "PARANA\u00cdBA", "cargo": "Vereador", "partido": "PDT", "situacaoTotalizacao": "Concorrendo", "txLink": "http://divulgacandcontas.tse.jus.br/divulga/#/candidato/2020/2030402020/91251/120001123699"}], "substituto": null, "motivos": null, "codigoSituacaoCandidato": 8, "descricaoSituacaoCandidato": "CADASTRADO", "st_SUBSTITUIDO": false, "descricaoNaturalidade": "MS-PARANA\u00cdBA", "cnpjcampanha": "39014517000175", "gastoCampanha": 0.0, "st_DIVULGA_ARQUIVOS": false, "st_MOTIVO_ABUSO_PODER": false, "st_DIVULGA_BENS": true, "st_MOTIVO_IND_PARTIDO": false, "st_MOTIVO_COMPRA_VOTO": false, "st_MOTIVO_CONDUTA_VEDADA": false, "st_MOTIVO_GASTO_ILICITO": false, "ds_MOTIVO_OUTROS": null, "st_MOTIVO_AUSENCIA_REQUISITO": false, "st_DIVULGA": true, "st_REELEICAO": false, "st_MOTIVO_FICHA_LIMPA": false}