{"id": 120000850100, "nomeUrna": "CHIRU SILVA", "numero": 14556, "idCandidatoSuperior": 0, "nomeCompleto": "HENRIQUE PAIS DA SILVA", "descricaoSexo": "MASC.", "dataDeNascimento": "1962-01-24", "tituloEleitor": "013239671988", "cpf": "28650816134", "descricaoEstadoCivil": "Casado(a)", "descricaoCorRaca": "PRETA", "descricaoSituacao": "Aguardando julgamento", "nacionalidade": "Brasileira nata", "grauInstrucao": "Superior completo", "ocupacao": "Administrador", "gastoCampanha1T": 732621.66, "gastoCampanha2T": 0, "sgUfNascimento": "MS", "nomeMunicipioNascimento": "CAMPO GRANDE", "localCandidatura": "CAMPO GRANDE", "ufCandidatura": "90514", "ufSuperiorCandidatura": "MS", "dataUltimaAtualizacao": "2020-10-13", "fotoUrl": "http://divulgacandcontas.tse.jus.br/candidaturas/oficial/2020/MS/90514/426/candidatos/550306/foto.jpg", "fotoDataUltimaAtualizacao": null, "descricaoTotalizacao": "Concorrendo", "nomeColigacao": "PTB", "composicaoColigacao": "**", "numeroProcessoDrap": "06001505420206120044", "numeroProcessoDrapEncrypt": "84753052aed0f8e05f826e62a70b508f14e829c297ba89e33c94518a892104aaa51fc66567b5510d", "numeroProcesso": "06001756720206120044", "numeroProcessoEncrypt": "81df9d980484ec8d6f421ea39c2ca06314e829c297ba89e33c94518a892104aaa51fc66567b5510d", "numeroProcessoPrestContas": null, "numeroProcessoPrestContasEncrypt": null, "numeroProtocolo": null, "cargo": {"codigo": 13, "sigla": null, "nome": "Vereador", "codSuperior": 0, "titular": true, "contagem": 0}, "bens": [{"ordem": 2, "descricao": "MOTO HONDA NXR  150 BROS, PLACA HSP 9337, ANO 2005, COR VERMELHA, RN 00885365232 ", "descricaoDeTipoDeBem": "Ve\u00edculo automotor terrestre: caminh\u00e3o, autom\u00f3vel, moto, etc.", "valor": 20000.0, "dataUltimaAtualizacao": "2020-09-23"}, {"ordem": 1, "descricao": "CHEVROLET ONIX 1.0, PLACA PXY 2673, COR PRATA, RN 01090414770, ANO 2016", "descricaoDeTipoDeBem": "Ve\u00edculo automotor terrestre: caminh\u00e3o, autom\u00f3vel, moto, etc.", "valor": 40000.0, "dataUltimaAtualizacao": "2020-09-23"}], "totalDeBens": 60000, "vices": null, "partido": {"numero": 14, "sigla": "PTB", "nome": "Partido Trabalhista Brasileiro"}, "eleicao": {"id": 2030402020, "siglaUF": null, "localidadeSgUe": null, "ano": 2020, "codigo": null, "nomeEleicao": null, "tipoEleicao": null, "turno": null, "tipoAbrangencia": null, "dataEleicao": null, "codSituacaoEleicao": null, "descricaoSituacaoEleicao": null, "descricaoEleicao": "2020"}, "emails": ["CHIRUCOMUNIDADE@GMAIL.COM"], "sites": [], "arquivos": [{"idArquivo": 120007300600, "nome": "13_1600788456177.pdf", "url": "candidaturas/oficial/2020/MS/90514/426/candidatos/550306/", "tipo": "pdf", "codTipo": "13", "fullFilePath": null, "fileInputStream": null, "fileByteArray": null}, {"idArquivo": 120007300599, "nome": "14_1600788499979.pdf", "url": "candidaturas/oficial/2020/MS/90514/426/candidatos/550306/", "tipo": "pdf", "codTipo": "14", "fullFilePath": null, "fileInputStream": null, "fileByteArray": null}, {"idArquivo": 120007300598, "nome": "11_1600788525552.pdf", "url": "candidaturas/oficial/2020/MS/90514/426/candidatos/550306/", "tipo": "pdf", "codTipo": "11", "fullFilePath": null, "fileInputStream": null, "fileByteArray": null}, {"idArquivo": 120007300597, "nome": "12_1600788527723.pdf", "url": "candidaturas/oficial/2020/MS/90514/426/candidatos/550306/", "tipo": "pdf", "codTipo": "12", "fullFilePath": null, "fileInputStream": null, "fileByteArray": null}], "eleicoesAnteriores": [{"nrAno": 2020, "id": "120000850100", "nomeUrna": "CHIRU SILVA", "nomeCandidato": "HENRIQUE PAIS DA SILVA", "idEleicao": "2030402020", "sgUe": "90514", "local": "CAMPO GRANDE", "cargo": "Vereador", "partido": "PTB", "situacaoTotalizacao": "Concorrendo", "txLink": "http://divulgacandcontas.tse.jus.br/divulga/#/candidato/2020/2030402020/90514/120000850100"}], "substituto": null, "motivos": null, "codigoSituacaoCandidato": 8, "descricaoSituacaoCandidato": "CADASTRADO", "st_SUBSTITUIDO": false, "descricaoNaturalidade": "MS-CAMPO GRANDE", "st_MOTIVO_AUSENCIA_REQUISITO": false, "st_MOTIVO_CONDUTA_VEDADA": false, "cnpjcampanha": "38753643000189", "gastoCampanha": 0.0, "st_MOTIVO_ABUSO_PODER": false, "st_MOTIVO_COMPRA_VOTO": false, "ds_MOTIVO_OUTROS": null, "st_MOTIVO_GASTO_ILICITO": false, "st_MOTIVO_IND_PARTIDO": false, "st_MOTIVO_FICHA_LIMPA": false, "st_DIVULGA_ARQUIVOS": false, "st_DIVULGA_BENS": true, "st_DIVULGA": true, "st_REELEICAO": false}