{"id": 120001071538, "nomeUrna": "DILZA PEREIRA", "numero": 15015, "idCandidatoSuperior": 0, "nomeCompleto": "DILZA PEREIRA DA SILVA", "descricaoSexo": "FEM.", "dataDeNascimento": "1966-05-04", "tituloEleitor": "009202021910", "cpf": "36603376172", "descricaoEstadoCivil": "Casado(a)", "descricaoCorRaca": "PARDA", "descricaoSituacao": "Deferido", "nacionalidade": "Brasileira nata", "grauInstrucao": "Superior completo", "ocupacao": "Professor de Ensino Fundamental", "gastoCampanha1T": 30714.55, "gastoCampanha2T": 0, "sgUfNascimento": "MS", "nomeMunicipioNascimento": "RIO VERDE DE MATO GROSSO", "localCandidatura": "RIO VERDE DE MATO GROSSO", "ufCandidatura": "91472", "ufSuperiorCandidatura": "MS", "dataUltimaAtualizacao": "2020-10-14", "fotoUrl": "http://divulgacandcontas.tse.jus.br/candidaturas/oficial/2020/MS/91472/426/candidatos/642428/foto.jpg", "fotoDataUltimaAtualizacao": null, "descricaoTotalizacao": "Concorrendo", "nomeColigacao": "MDB", "composicaoColigacao": "**", "numeroProcessoDrap": "06000974520206120021", "numeroProcessoDrapEncrypt": "a1f891e36d8bda1d0deaeaf29d29a4cd697a9030ad70a71a3c94518a892104aaa51fc66567b5510d", "numeroProcesso": "06001338720206120021", "numeroProcessoEncrypt": "87890490e5e3bf586f421ea39c2ca063697a9030ad70a71a3c94518a892104aaa51fc66567b5510d", "numeroProcessoPrestContas": null, "numeroProcessoPrestContasEncrypt": null, "numeroProtocolo": null, "cargo": {"codigo": 13, "sigla": null, "nome": "Vereador", "codSuperior": 0, "titular": true, "contagem": 0}, "bens": [{"ordem": 3, "descricao": "LOTE DE TERRENO  DETERMINADO SOB O N\u00ba 01, DA QUADRA N\u00ba 36, LOTEAMENTO JARDIM JOS\u00c9 ANTONIO, AREA 373,16 M\u00b2, EM RIO VERDE DE MATO GROSSO/MS", "descricaoDeTipoDeBem": "Terreno", "valor": 7000.0, "dataUltimaAtualizacao": "2020-09-25"}, {"ordem": 1, "descricao": "MOTONETA HONDA BIZ 125, ANO/FAB 2017, ANO/MOD 2018, COR BRANCA, PLACA QAG1583, RENAVAM 01139296091, CHASSI 9C2JC4830JR101255", "descricaoDeTipoDeBem": "Ve\u00edculo automotor terrestre: caminh\u00e3o, autom\u00f3vel, moto, etc.", "valor": 9630.0, "dataUltimaAtualizacao": "2020-09-25"}, {"ordem": 2, "descricao": "LOTE DE TERRENO URBANO SOB O N\u00ba 382, DA QUADRA N\u00ba 38, SITUADO A RUA ALMIRANTE TAMANDAR\u00c9, AREA 400,00 M\u00b2, RIO VERDE DE MATO GROSSO/MS", "descricaoDeTipoDeBem": "Terreno", "valor": 12000.0, "dataUltimaAtualizacao": "2020-09-25"}], "totalDeBens": 28630, "vices": null, "partido": {"numero": 15, "sigla": "MDB", "nome": "Movimento Democr\u00e1tico Brasileiro"}, "eleicao": {"id": 2030402020, "siglaUF": null, "localidadeSgUe": null, "ano": 2020, "codigo": null, "nomeEleicao": null, "tipoEleicao": null, "turno": null, "tipoAbrangencia": null, "dataEleicao": null, "codSituacaoEleicao": null, "descricaoSituacaoEleicao": null, "descricaoEleicao": "2020"}, "emails": ["mjadvogados1@gmail.com"], "sites": [], "arquivos": [{"idArquivo": 120008813329, "nome": "12_1600868199738.pdf", "url": "candidaturas/oficial/2020/MS/91472/426/candidatos/642428/", "tipo": "pdf", "codTipo": "12", "fullFilePath": null, "fileInputStream": null, "fileByteArray": null}, {"idArquivo": 120008813328, "nome": "11_1600868196671.pdf", "url": "candidaturas/oficial/2020/MS/91472/426/candidatos/642428/", "tipo": "pdf", "codTipo": "11", "fullFilePath": null, "fileInputStream": null, "fileByteArray": null}, {"idArquivo": 120008813325, "nome": "14_1600868202954.pdf", "url": "candidaturas/oficial/2020/MS/91472/426/candidatos/642428/", "tipo": "pdf", "codTipo": "14", "fullFilePath": null, "fileInputStream": null, "fileByteArray": null}, {"idArquivo": 120008813323, "nome": "13_1600868202037.pdf", "url": "candidaturas/oficial/2020/MS/91472/426/candidatos/642428/", "tipo": "pdf", "codTipo": "13", "fullFilePath": null, "fileInputStream": null, "fileByteArray": null}], "eleicoesAnteriores": [{"nrAno": 2020, "id": "120001071538", "nomeUrna": "DILZA PEREIRA", "nomeCandidato": "DILZA PEREIRA DA SILVA", "idEleicao": "2030402020", "sgUe": "91472", "local": "RIO VERDE DE MATO GROSSO", "cargo": "Vereador", "partido": "MDB", "situacaoTotalizacao": "Concorrendo", "txLink": "http://divulgacandcontas.tse.jus.br/divulga/#/candidato/2020/2030402020/91472/120001071538"}], "substituto": null, "motivos": null, "codigoSituacaoCandidato": 2, "descricaoSituacaoCandidato": "APTO", "st_SUBSTITUIDO": false, "descricaoNaturalidade": "MS-RIO VERDE DE MATO GROSSO", "st_MOTIVO_AUSENCIA_REQUISITO": false, "st_MOTIVO_CONDUTA_VEDADA": false, "cnpjcampanha": "39045129000151", "gastoCampanha": 0.0, "st_MOTIVO_ABUSO_PODER": false, "st_MOTIVO_COMPRA_VOTO": false, "ds_MOTIVO_OUTROS": null, "st_MOTIVO_GASTO_ILICITO": false, "st_MOTIVO_IND_PARTIDO": false, "st_MOTIVO_FICHA_LIMPA": false, "st_DIVULGA_ARQUIVOS": false, "st_DIVULGA_BENS": true, "st_DIVULGA": true, "st_REELEICAO": false}