{"id": 120000640907, "nomeUrna": "PAULO RICARTE", "numero": 30333, "idCandidatoSuperior": 0, "nomeCompleto": "PAULO DA SILVA RICARTE", "descricaoSexo": "MASC.", "dataDeNascimento": "1963-05-05", "tituloEleitor": "000501551970", "cpf": "28523326120", "descricaoEstadoCivil": "Divorciado(a)", "descricaoCorRaca": "PARDA", "descricaoSituacao": "Aguardando julgamento", "nacionalidade": "Brasileira nata", "grauInstrucao": "Superior completo", "ocupacao": "Advogado", "gastoCampanha1T": 732621.66, "gastoCampanha2T": 0, "sgUfNascimento": "MS", "nomeMunicipioNascimento": "CAMPO GRANDE", "localCandidatura": "CAMPO GRANDE", "ufCandidatura": "90514", "ufSuperiorCandidatura": "MS", "dataUltimaAtualizacao": "2020-10-10", "fotoUrl": "http://divulgacandcontas.tse.jus.br/candidaturas/oficial/2020/MS/90514/426/candidatos/166806/Foto de urna (2).jpg", "fotoDataUltimaAtualizacao": null, "descricaoTotalizacao": "Concorrendo", "nomeColigacao": "NOVO", "composicaoColigacao": "**", "numeroProcessoDrap": "06000264420206120053", "numeroProcessoDrapEncrypt": "d75d7d0a706cc81e5f826e62a70b508fd6bcbe1212da3ea53c94518a892104aaa51fc66567b5510d", "numeroProcesso": "06000308120206120053", "numeroProcessoEncrypt": "7c29348687b83e8258c85008bde2a00dd6bcbe1212da3ea53c94518a892104aaa51fc66567b5510d", "numeroProcessoPrestContas": null, "numeroProcessoPrestContasEncrypt": null, "numeroProtocolo": null, "cargo": {"codigo": 13, "sigla": null, "nome": "Vereador", "codSuperior": 0, "titular": true, "contagem": 0}, "bens": [{"ordem": 2, "descricao": "1)Im\u00f3vel terreno 12 x 33, 412,5 m2 Q.26, L 19 com edifica\u00e7\u00e3o de casa de 70 m2 \u00bf Rua Itapiranga n\u00ba 232, Bairro Jardim Montevideo, Campo Grande MS", "descricaoDeTipoDeBem": "Terreno", "valor": 50000.0, "dataUltimaAtualizacao": "2020-09-15"}, {"ordem": 1, "descricao": "2)Lote de terreno n\u00ba 08 da Quadra 23, Vila dos Ferrovi\u00e1rios, Rua Ant\u00f4nio Penelli 10x45m2 Tr\u00eas Lagoas, MS, Registro Cart\u00f3rio de 1\u00ba Oficio n\u00ba Matricula", "descricaoDeTipoDeBem": "Terreno", "valor": 15000.0, "dataUltimaAtualizacao": "2020-09-15"}], "totalDeBens": 65000, "vices": null, "partido": {"numero": 30, "sigla": "NOVO", "nome": "Partido Novo"}, "eleicao": {"id": 2030402020, "siglaUF": null, "localidadeSgUe": null, "ano": 2020, "codigo": null, "nomeEleicao": null, "tipoEleicao": null, "turno": null, "tipoAbrangencia": null, "dataEleicao": null, "codSituacaoEleicao": null, "descricaoSituacaoEleicao": null, "descricaoEleicao": "2020"}, "emails": ["paulosilvaricarte@hotmail.com"], "sites": ["https://instagram.com/Ricarte_Paulo", "https://www.facebook.com/pauloricarte30novo"], "arquivos": [{"idArquivo": 120007252896, "nome": "pje-12c2673e-Certid\u00e3o criminal da Justi\u00e7a Federal de 2\u00ba grau.pdf", "url": "candidaturas/oficial/2020/MS/90514/2030402020/120000640907/", "tipo": "pdf", "codTipo": "12", "fullFilePath": null, "fileInputStream": null, "fileByteArray": null}, {"idArquivo": 120007218868, "nome": "pje-d762b246-Certid\u00e3o criminal da Justi\u00e7a Federal de 1\u00ba grau.pdf", "url": "candidaturas/oficial/2020/MS/90514/2030402020/120000640907/", "tipo": "pdf", "codTipo": "11", "fullFilePath": null, "fileInputStream": null, "fileByteArray": null}, {"idArquivo": 120007207473, "nome": "pje-b45e570f-Certid\u00e3o criminal da Justi\u00e7a Estadual de 2\u00ba grau.pdf", "url": "candidaturas/oficial/2020/MS/90514/2030402020/120000640907/", "tipo": "pdf", "codTipo": "14", "fullFilePath": null, "fileInputStream": null, "fileByteArray": null}, {"idArquivo": 120007207472, "nome": "pje-c0b5e45c-Certid\u00e3o criminal da Justi\u00e7a Estadual de 1\u00ba grau.pdf", "url": "candidaturas/oficial/2020/MS/90514/2030402020/120000640907/", "tipo": "pdf", "codTipo": "13", "fullFilePath": null, "fileInputStream": null, "fileByteArray": null}, {"idArquivo": 120005868038, "nome": "13_1599594163238.pdf", "url": "candidaturas/oficial/2020/MS/90514/426/candidatos/166806/", "tipo": "pdf", "codTipo": "13", "fullFilePath": null, "fileInputStream": null, "fileByteArray": null}, {"idArquivo": 120005868037, "nome": "12_1599594163097.pdf", "url": "candidaturas/oficial/2020/MS/90514/426/candidatos/166806/", "tipo": "pdf", "codTipo": "12", "fullFilePath": null, "fileInputStream": null, "fileByteArray": null}, {"idArquivo": 120005868035, "nome": "14_1599594163398.pdf", "url": "candidaturas/oficial/2020/MS/90514/426/candidatos/166806/", "tipo": "pdf", "codTipo": "14", "fullFilePath": null, "fileInputStream": null, "fileByteArray": null}, {"idArquivo": 120005868034, "nome": "11_1599594162943.pdf", "url": "candidaturas/oficial/2020/MS/90514/426/candidatos/166806/", "tipo": "pdf", "codTipo": "11", "fullFilePath": null, "fileInputStream": null, "fileByteArray": null}], "eleicoesAnteriores": [{"nrAno": 2020, "id": "120000640907", "nomeUrna": "PAULO RICARTE", "nomeCandidato": "PAULO DA SILVA RICARTE", "idEleicao": "2030402020", "sgUe": "90514", "local": "CAMPO GRANDE", "cargo": "Vereador", "partido": "NOVO", "situacaoTotalizacao": "Concorrendo", "txLink": "http://divulgacandcontas.tse.jus.br/divulga/#/candidato/2020/2030402020/90514/120000640907"}], "substituto": null, "motivos": null, "codigoSituacaoCandidato": 8, "descricaoSituacaoCandidato": "CADASTRADO", "st_SUBSTITUIDO": false, "descricaoNaturalidade": "MS-CAMPO GRANDE", "cnpjcampanha": "38528572000110", "gastoCampanha": 0.0, "st_DIVULGA_ARQUIVOS": false, "st_MOTIVO_ABUSO_PODER": false, "st_DIVULGA_BENS": true, "st_MOTIVO_IND_PARTIDO": false, "st_MOTIVO_COMPRA_VOTO": false, "st_MOTIVO_CONDUTA_VEDADA": false, "st_MOTIVO_GASTO_ILICITO": false, "ds_MOTIVO_OUTROS": null, "st_MOTIVO_AUSENCIA_REQUISITO": false, "st_DIVULGA": true, "st_REELEICAO": false, "st_MOTIVO_FICHA_LIMPA": false}