{"id": 120001156498, "nomeUrna": "EVARISTO FARIAS", "numero": 19123, "idCandidatoSuperior": 0, "nomeCompleto": "EVARISTO APARECIDO FARIAS", "descricaoSexo": "MASC.", "dataDeNascimento": "1956-10-15", "tituloEleitor": "003430691937", "cpf": "11056290153", "descricaoEstadoCivil": "Casado(a)", "descricaoCorRaca": "BRANCA", "descricaoSituacao": "Aguardando julgamento", "nacionalidade": "Brasileira nata", "grauInstrucao": "Ensino Fundamental incompleto", "ocupacao": "Pecuarista", "gastoCampanha1T": 12307.75, "gastoCampanha2T": 0, "sgUfNascimento": "SP", "nomeMunicipioNascimento": "MURUTINGA DO SUL", "localCandidatura": "DEOD\u00c1POLIS", "ufCandidatura": "91758", "ufSuperiorCandidatura": "MS", "dataUltimaAtualizacao": "2020-09-27", "fotoUrl": "http://divulgacandcontas.tse.jus.br/candidaturas/oficial/2020/MS/91758/426/candidatos/807161/foto.JPG", "fotoDataUltimaAtualizacao": null, "descricaoTotalizacao": "Concorrendo", "nomeColigacao": "PODE", "composicaoColigacao": "**", "numeroProcessoDrap": "06001108720206120039", "numeroProcessoDrapEncrypt": "060c92639e011e326f421ea39c2ca06370684d6a78a5080d3c94518a892104aaa51fc66567b5510d", "numeroProcesso": "06001645320206120039", "numeroProcessoEncrypt": "4316bec90f9c471e9beb4e5b4f649f4970684d6a78a5080d3c94518a892104aaa51fc66567b5510d", "numeroProcessoPrestContas": null, "numeroProcessoPrestContasEncrypt": null, "numeroProtocolo": null, "cargo": {"codigo": 13, "sigla": null, "nome": "Vereador", "codSuperior": 0, "titular": true, "contagem": 0}, "bens": [{"ordem": 3, "descricao": "PROPRIEDADE RURAL EM DEODAPOLIS ", "descricaoDeTipoDeBem": "Outros bens im\u00f3veis", "valor": 750000.0, "dataUltimaAtualizacao": "2020-09-25"}, {"ordem": 4, "descricao": "PROPRIEDADE RURAL EM NOVA ANDRADINA ", "descricaoDeTipoDeBem": "Outros bens im\u00f3veis", "valor": 600000.0, "dataUltimaAtualizacao": "2020-09-25"}, {"ordem": 2, "descricao": "TOYOTA COROLLA ANO 2010 MODELO 2011 PLACAS AYE 1130", "descricaoDeTipoDeBem": "Ve\u00edculo automotor terrestre: caminh\u00e3o, autom\u00f3vel, moto, etc.", "valor": 45000.0, "dataUltimaAtualizacao": "2020-09-25"}, {"ordem": 1, "descricao": "F 4000 ANO MODELO 1993 PLACAS ADR 5481", "descricaoDeTipoDeBem": "Ve\u00edculo automotor terrestre: caminh\u00e3o, autom\u00f3vel, moto, etc.", "valor": 60000.0, "dataUltimaAtualizacao": "2020-09-25"}], "totalDeBens": 1455000, "vices": null, "partido": {"numero": 19, "sigla": "PODE", "nome": "Podemos"}, "eleicao": {"id": 2030402020, "siglaUF": null, "localidadeSgUe": null, "ano": 2020, "codigo": null, "nomeEleicao": null, "tipoEleicao": null, "turno": null, "tipoAbrangencia": null, "dataEleicao": null, "codSituacaoEleicao": null, "descricaoSituacaoEleicao": null, "descricaoEleicao": "2020"}, "emails": ["COLIGACAOMDBPODE@GMAIL.COM"], "sites": [], "arquivos": [{"idArquivo": 120009399350, "nome": "11_1601074523590.pdf", "url": "candidaturas/oficial/2020/MS/91758/426/candidatos/807161/", "tipo": "pdf", "codTipo": "11", "fullFilePath": null, "fileInputStream": null, "fileByteArray": null}, {"idArquivo": 120009399349, "nome": "14_1601074505502.pdf", "url": "candidaturas/oficial/2020/MS/91758/426/candidatos/807161/", "tipo": "pdf", "codTipo": "14", "fullFilePath": null, "fileInputStream": null, "fileByteArray": null}, {"idArquivo": 120009399348, "nome": "12_1601074552093.pdf", "url": "candidaturas/oficial/2020/MS/91758/426/candidatos/807161/", "tipo": "pdf", "codTipo": "12", "fullFilePath": null, "fileInputStream": null, "fileByteArray": null}, {"idArquivo": 120009399347, "nome": "13_1601073679477.pdf", "url": "candidaturas/oficial/2020/MS/91758/426/candidatos/807161/", "tipo": "pdf", "codTipo": "13", "fullFilePath": null, "fileInputStream": null, "fileByteArray": null}], "eleicoesAnteriores": [{"nrAno": 2020, "id": "120001156498", "nomeUrna": "EVARISTO FARIAS", "nomeCandidato": "EVARISTO APARECIDO FARIAS", "idEleicao": "2030402020", "sgUe": "91758", "local": "DEOD\u00c1POLIS", "cargo": "Vereador", "partido": "PODE", "situacaoTotalizacao": "Concorrendo", "txLink": "http://divulgacandcontas.tse.jus.br/divulga/#/candidato/2020/2030402020/91758/120001156498"}], "substituto": null, "motivos": null, "codigoSituacaoCandidato": 8, "descricaoSituacaoCandidato": "CADASTRADO", "st_SUBSTITUIDO": false, "descricaoNaturalidade": "SP-MURUTINGA DO SUL", "st_MOTIVO_AUSENCIA_REQUISITO": false, "st_MOTIVO_CONDUTA_VEDADA": false, "cnpjcampanha": "39039593000135", "gastoCampanha": 0.0, "st_MOTIVO_ABUSO_PODER": false, "st_MOTIVO_COMPRA_VOTO": false, "ds_MOTIVO_OUTROS": null, "st_MOTIVO_GASTO_ILICITO": false, "st_MOTIVO_IND_PARTIDO": false, "st_MOTIVO_FICHA_LIMPA": false, "st_DIVULGA_ARQUIVOS": false, "st_DIVULGA_BENS": true, "st_DIVULGA": true, "st_REELEICAO": false}